pydough/__init__.py
pydough/configs/README.md
pydough/configs/__init__.py
pydough/configs/pydough_configs.py
pydough/configs/session.py
pydough/conversion/README.md
pydough/conversion/__init__.py
pydough/conversion/agg_removal.py
pydough/conversion/agg_split.py
pydough/conversion/column_bubbler.py
pydough/conversion/filter_pushdown.py
pydough/conversion/hybrid_connection.py
pydough/conversion/hybrid_correlation_extraction.py
pydough/conversion/hybrid_decorrelater.py
pydough/conversion/hybrid_expressions.py
pydough/conversion/hybrid_operations.py
pydough/conversion/hybrid_syncretizer.py
pydough/conversion/hybrid_translator.py
pydough/conversion/hybrid_tree.py
pydough/conversion/join_aggregate_transpose.py
pydough/conversion/join_key_substitution.py
pydough/conversion/masking_shuttles.py
pydough/conversion/merge_projects.py
pydough/conversion/projection_pullup.py
pydough/conversion/relational_converter.py
pydough/conversion/relational_simplification.py
pydough/database_connectors/README.md
pydough/database_connectors/__init__.py
pydough/database_connectors/builtin_databases.py
pydough/database_connectors/database_connector.py
pydough/database_connectors/db_types.py
pydough/database_connectors/empty_connection.py
pydough/errors/__init__.py
pydough/errors/error_types.py
pydough/errors/error_utils.py
pydough/errors/pydough_error_builder.py
pydough/evaluation/README.md
pydough/evaluation/__init__.py
pydough/evaluation/evaluate_unqualified.py
pydough/exploration/README.md
pydough/exploration/__init__.py
pydough/exploration/explain.py
pydough/exploration/structure.py
pydough/exploration/term.py
pydough/jupyter_extensions/README.md
pydough/jupyter_extensions/__init__.py
pydough/jupyter_extensions/pydough_magic.py
pydough/logger/README.md
pydough/logger/__init__.py
pydough/logger/logger.py
pydough/mask_server/__init__.py
pydough/mask_server/mask_server.py
pydough/mask_server/mask_server_candidate_visitor.py
pydough/mask_server/mask_server_rewrite_shuttle.py
pydough-1.0.17.dist-info/METADATA
pydough-1.0.17.dist-info/WHEEL
pydough-1.0.17.dist-info/licenses/LICENSE
pydough-1.0.17.dist-info/RECORD
