Metadata-Version: 2.4
Name: pydough
Version: 1.0.17
Summary: Analytics DSL for Python
Project-URL: Repository, https://github.com/bodo-ai/PyDough
Author: Bodo.ai
License-File: LICENSE
Keywords: analytics
Classifier: Development Status :: 4 - Beta
Classifier: Intended Audience :: Developers
Classifier: License :: OSI Approved :: Apache Software License
Classifier: Operating System :: OS Independent
Classifier: Programming Language :: Python
Classifier: Programming Language :: Python :: 3.10
Classifier: Programming Language :: Python :: 3.11
Classifier: Programming Language :: Python :: 3.12
Requires-Python: >=3.10
Requires-Dist: jupyterlab
Requires-Dist: pandas>=2.0.0
Requires-Dist: pytz
Requires-Dist: sqlglot==26.7.0
Provides-Extra: mysql
Requires-Dist: mysql-connector-python; extra == 'mysql'
Provides-Extra: postgres
Requires-Dist: psycopg2-binary; extra == 'postgres'
Provides-Extra: server
Requires-Dist: fastapi; extra == 'server'
Requires-Dist: httpx; extra == 'server'
Requires-Dist: uvicorn; extra == 'server'
Provides-Extra: snowflake
Requires-Dist: snowflake-connector-python[pandas]; extra == 'snowflake'
